torob_client/__init__.py
torob_client/api.py
torob_client-1.0.dist-info/LICENSE
torob_client-1.0.dist-info/METADATA
torob_client-1.0.dist-info/WHEEL
torob_client-1.0.dist-info/top_level.txt
torob_client-1.0.dist-info/RECORD
