Metadata-Version: 2.1
Name: torob-client
Version: 1.0
Summary: A Python client for interacting with the Torob API to fetch products data.
Home-page: https://github.com/ahur4/torob-client
Author: Ahur4
Author-email: ahur4.rahmani@gmail.com
Keywords: webscraping,crawling,data science,data analyse
Classifier: Programming Language :: Python :: 3
Classifier: License :: OSI Approved :: MIT License
Classifier: Operating System :: OS Independent
Requires-Python: >=3.6
License-File: LICENSE
Requires-Dist: requests ==2.32.3
